{"__schema":{"types":[{"kind":"OBJECT","name":"StopPlaceRegister","possibleTypes":null},{"kind":"INTERFACE","name":"StopPlaceInterface","possibleTypes":[{"name":"StopPlace"},{"name":"ParentStopPlace"}]},{"kind":"OBJECT","name":"PlaceEquipments","possibleTypes":null},{"kind":"SCALAR","name":"String","possibleTypes":null},{"kind":"OBJECT","name":"WaitingRoomEquipment","possibleTypes":null},{"kind":"SCALAR","name":"BigInteger","possibleTypes":null},{"kind":"SCALAR","name":"Boolean","possibleTypes":null},{"kind":"OBJECT","name":"SanitaryEquipment","possibleTypes":null},{"kind":"ENUM","name":"gender","possibleTypes":null},{"kind":"OBJECT","name":"TicketingEquipment","possibleTypes":null},{"kind":"OBJECT","name":"ShelterEquipment","possibleTypes":null},{"kind":"OBJECT","name":"CycleStorageEquipment","possibleTypes":null},{"kind":"ENUM","name":"cycleStorageType","possibleTypes":null},{"kind":"OBJECT","name":"GeneralSign","possibleTypes":null},{"kind":"OBJECT","name":"PrivateCode","possibleTypes":null},{"kind":"OBJECT","name":"EmbeddableMultilingualString","possibleTypes":null},{"kind":"ENUM","name":"signContentType","possibleTypes":null},{"kind":"OBJECT","name":"AccessibilityAssessment","possibleTypes":null},{"kind":"OBJECT","name":"AccessibilityLimitations","possibleTypes":null},{"kind":"ENUM","name":"LimitationStatusType","possibleTypes":null},{"kind":"OBJECT","name":"GeoJSON","possibleTypes":null},{"kind":"ENUM","name":"GeoJSONType","possibleTypes":null},{"kind":"SCALAR","name":"Coordinates","possibleTypes":null},{"kind":"OBJECT","name":"KeyValues","possibleTypes":null},{"kind":"OBJECT","name":"TopographicPlace","possibleTypes":null},{"kind":"ENUM","name":"TopographicPlaceType","possibleTypes":null},{"kind":"OBJECT","name":"ValidBetween","possibleTypes":null},{"kind":"SCALAR","name":"DateTime","possibleTypes":null},{"kind":"OBJECT","name":"AlternativeName","possibleTypes":null},{"kind":"ENUM","name":"nameType","possibleTypes":null},{"kind":"OBJECT","name":"TariffZone","possibleTypes":null},{"kind":"OBJECT","name":"Tag","possibleTypes":null},{"kind":"SCALAR","name":"Int","possibleTypes":null},{"kind":"ENUM","name":"StopPlaceType","possibleTypes":null},{"kind":"SCALAR","name":"BigDecimal","possibleTypes":null},{"kind":"OBJECT","name":"PathLink","possibleTypes":null},{"kind":"OBJECT","name":"PathLinkEnd","possibleTypes":null},{"kind":"OBJECT","name":"EntityRef","possibleTypes":null},{"kind":"OBJECT","name":"AddressablePlace","possibleTypes":null},{"kind":"OBJECT","name":"TransferDuration","possibleTypes":null},{"kind":"OBJECT","name":"Parking","possibleTypes":null},{"kind":"ENUM","name":"ParkingType","possibleTypes":null},{"kind":"ENUM","name":"ParkingVehicleType","possibleTypes":null},{"kind":"ENUM","name":"ParkingLayoutType","possibleTypes":null},{"kind":"ENUM","name":"ParkingReservationType","possibleTypes":null},{"kind":"OBJECT","name":"ParkingProperties","possibleTypes":null},{"kind":"ENUM","name":"ParkingUserType","possibleTypes":null},{"kind":"OBJECT","name":"ParkingCapacity","possibleTypes":null},{"kind":"ENUM","name":"ParkingStayType","possibleTypes":null},{"kind":"OBJECT","name":"ParkingArea","possibleTypes":null},{"kind":"OBJECT","name":"TransportModes","possibleTypes":null},{"kind":"OBJECT","name":"AuthorizationCheck","possibleTypes":null},{"kind":"OBJECT","name":"StopPlaceMutation","possibleTypes":null},{"kind":"OBJECT","name":"StopPlace","possibleTypes":null},{"kind":"ENUM","name":"TransportModeType","possibleTypes":null},{"kind":"ENUM","name":"SubmodeType","possibleTypes":null},{"kind":"ENUM","name":"InterchangeWeightingType","possibleTypes":null},{"kind":"OBJECT","name":"Quay","possibleTypes":null},{"kind":"INPUT_OBJECT","name":"StopPlaceInput","possibleTypes":null},{"kind":"INPUT_OBJECT","name":"EmbeddableMultilingualStringInput","possibleTypes":null},{"kind":"INPUT_OBJECT","name":"GeoJSONInput","possibleTypes":null},{"kind":"INPUT_OBJECT","name":"AlternativeNameInput","possibleTypes":null},{"kind":"INPUT_OBJECT","name":"PlaceEquipmentsInput","possibleTypes":null},{"kind":"INPUT_OBJECT","name":"WaitingRoomEquipmentInput","possibleTypes":null},{"kind":"INPUT_OBJECT","name":"SanitaryEquipmentInput","possibleTypes":null},{"kind":"INPUT_OBJECT","name":"TicketingEquipmentInput","possibleTypes":null},{"kind":"INPUT_OBJECT","name":"ShelterEquipmentInput","possibleTypes":null},{"kind":"INPUT_OBJECT","name":"CycleStorageEquipmentInput","possibleTypes":null},{"kind":"INPUT_OBJECT","name":"GeneralSignInput","possibleTypes":null},{"kind":"INPUT_OBJECT","name":"PrivateCodeInput","possibleTypes":null},{"kind":"INPUT_OBJECT","name":"KeyValuesInput","possibleTypes":null},{"kind":"INPUT_OBJECT","name":"AccessibilityAssessmentInput","possibleTypes":null},{"kind":"INPUT_OBJECT","name":"AccessibilityLimitationsInput","possibleTypes":null},{"kind":"INPUT_OBJECT","name":"TopographicPlaceInput","possibleTypes":null},{"kind":"INPUT_OBJECT","name":"QuayInput","possibleTypes":null},{"kind":"INPUT_OBJECT","name":"ValidBetweenInput","possibleTypes":null},{"kind":"OBJECT","name":"ParentStopPlace","possibleTypes":null},{"kind":"INPUT_OBJECT","name":"ParentStopPlaceInput","possibleTypes":null},{"kind":"INPUT_OBJECT","name":"PathLinkInput","possibleTypes":null},{"kind":"INPUT_OBJECT","name":"PathLinkEndInput","possibleTypes":null},{"kind":"INPUT_OBJECT","name":"EntityRefInput","possibleTypes":null},{"kind":"INPUT_OBJECT","name":"TransferDurationInput","possibleTypes":null},{"kind":"INPUT_OBJECT","name":"ParkingInput","possibleTypes":null},{"kind":"INPUT_OBJECT","name":"ParkingPropertiesInput","possibleTypes":null},{"kind":"INPUT_OBJECT","name":"ParkingCapacityInput","possibleTypes":null},{"kind":"INPUT_OBJECT","name":"ParkingAreaInput","possibleTypes":null},{"kind":"INPUT_OBJECT","name":"createMultiModalStopPlaceInput","possibleTypes":null},{"kind":"INPUT_OBJECT","name":"addToMultiModalStopPlaceInput","possibleTypes":null},{"kind":"OBJECT","name":"__Schema","possibleTypes":null},{"kind":"OBJECT","name":"__Type","possibleTypes":null},{"kind":"ENUM","name":"__TypeKind","possibleTypes":null},{"kind":"OBJECT","name":"__Field","possibleTypes":null},{"kind":"OBJECT","name":"__InputValue","possibleTypes":null},{"kind":"OBJECT","name":"__EnumValue","possibleTypes":null},{"kind":"OBJECT","name":"__Directive","possibleTypes":null},{"kind":"ENUM","name":"__DirectiveLocation","possibleTypes":null}]}}